BrawlMoon/__init__.py
BrawlMoon/abilities.py
BrawlMoon/basis.py
BrawlMoon/brawler.py
BrawlMoon/client.py
BrawlMoon/club.py
BrawlMoon/enums.py
BrawlMoon/errors.py
BrawlMoon/player.py
BrawlMoon/resp.py
BrawlMoon-0.1.0.dist-info/LICENSE
BrawlMoon-0.1.0.dist-info/METADATA
BrawlMoon-0.1.0.dist-info/WHEEL
BrawlMoon-0.1.0.dist-info/top_level.txt
BrawlMoon-0.1.0.dist-info/RECORD
