Metadata-Version: 2.1
Name: BrawlMoon
Version: 0.1.0
Summary: Handler for the Brawl Stars API
Home-page: https://github.com/Kyando2/BrawlMoon
Author: Kyando
Author-email: amehikoji@gmail.com
License: UNKNOWN
Platform: UNKNOWN
Classifier: Programming Language :: Python :: 3
Classifier: License :: OSI Approved :: MIT License
Classifier: Operating System :: OS Independent
Requires-Python: >=3.6
